oci_core/__init__.py
oci_core/bucket.py
oci_core/main.py
oci_core-0.0.79.dist-info/METADATA
oci_core-0.0.79.dist-info/WHEEL
oci_core-0.0.79.dist-info/top_level.txt
oci_core-0.0.79.dist-info/RECORD
