Metadata-Version: 2.1
Name: oci-core
Version: 0.0.79
Summary: OCI Core Helper
Home-page: https://bitbucket.oci.oraclecorp.com/projects/HWD/repos/hadoop/browse/etl/sharedLibs/oci_core
Author: Stone Zhong
Author-email: shidong.zhong@oracle.com
Classifier: Programming Language :: Python :: 3
Requires-Dist: oci
Requires-Dist: cachetools
